pycmpfit.cp37-win_amd64.pyd
pycmpfit-0.2.0.dist-info/METADATA
pycmpfit-0.2.0.dist-info/WHEEL
pycmpfit-0.2.0.dist-info/top_level.txt
pycmpfit-0.2.0.dist-info/RECORD
