Metadata-Version: 2.1
Name: pycmpfit
Version: 0.2.0
Summary: UNKNOWN
Home-page: https://github.com/cosmonaut/pycmpfit
Author: Nicholas Nell
Author-email: nicholas.nell@colorado.edu
License: UNKNOWN
Keywords: Scientific/Engineering
Platform: UNKNOWN
Requires: numpy
Provides: pycmpfit
